{
    "niv": {
        "branch": "master",
        "description": "Easy dependency management for Nix projects",
        "homepage": "https://github.com/nmattia/niv",
        "owner": "nmattia",
        "repo": "niv",
        "rev": "f73bf8d584148677b01859677a63191c31911eae",
        "sha256": "0jlmrx633jvqrqlyhlzpvdrnim128gc81q5psz2lpp2af8p8q9qs",
        "type": "tarball",
        "url": "https://github.com/nmattia/niv/archive/f73bf8d584148677b01859677a63191c31911eae.tar.gz",
        "url_template": "https://github.com/<owner>/<repo>/archive/<rev>.tar.gz"
    },
    "repos": {
        "branch": "master",
        "description": null,
        "homepage": null,
        "owner": "ttuegel",
        "repo": "repos",
        "rev": "7a132560ba119c3ea4b0b5cdc023eebdc7a0ab71",
        "sha256": "0cp3mjwnbi5nq2qs7w2dgfsn6ay7ifaknnq9jyh076l9jpipcqch",
        "type": "tarball",
        "url": "https://github.com/ttuegel/repos/archive/7a132560ba119c3ea4b0b5cdc023eebdc7a0ab71.tar.gz",
        "url_template": "https://github.com/<owner>/<repo>/archive/<rev>.tar.gz"
    }
}
